{
  "boards": [
    {
      "name": "Board of Directors",
      "members": [
        {
          "attributes": {
            "type": "Account",
            "url": "/services/data/v59.0/sobjects/Account/001Uf00000WkK6OIAV"
          },
          "Name": "Sonia Ancoli Israel",
          "Recognition_Amount_FY26__c": 36000,
          "Recognition_Amount_FY25__c": 36000,
          "JFSD_Board_Active__c": true
        },
        {
          "attributes": {
            "type": "Account",
            "url": "/services/data/v59.0/sobjects/Account/001Uf00000WkH3CIAV"
          },
          "Name": "Allie Hauser-Erickson",
          "Recognition_Amount_FY26__c": 18000,
          "Recognition_Amount_FY25__c": 16582,
          "JFSD_Board_Active__c": true
        },
        {
          "attributes": {
            "type": "Account",
            "url": "/services/data/v59.0/sobjects/Account/001Uf00000WkCZyIAN"
          },
          "Name": "Silvana Anna Christy",
          "Recognition_Amount_FY26__c": 12800,
          "Recognition_Amount_FY25__c": 11036,
          "JFSD_Board_Active__c": true
        },
        {
          "attributes": {
            "type": "Account",
            "url": "/services/data/v59.0/sobjects/Account/001Uf00000WkN0YIAV"
          },
          "Name": "Jeff M. Schindler",
          "Recognition_Amount_FY26__c": 12000,
          "Recognition_Amount_FY25__c": 12000,
          "JFSD_Board_Active__c": true
        },
        {
          "attributes": {
            "type": "Account",
            "url": "/services/data/v59.0/sobjects/Account/001Uf00000WkI6dIAF"
          },
          "Name": "Jack Maizel",
          "Recognition_Amount_FY26__c": 10250,
          "Recognition_Amount_FY25__c": 10000,
          "JFSD_Board_Active__c": true
        },
        {
          "attributes": {
            "type": "Account",
            "url": "/services/data/v59.0/sobjects/Account/001Uf00000WkTr8IAF"
          },
          "Name": "Kira Elizabeth Finkenberg",
          "Recognition_Amount_FY26__c": 10000,
          "Recognition_Amount_FY25__c": 10400,
          "JFSD_Board_Active__c": true
        },
        {
          "attributes": {
            "type": "Account",
            "url": "/services/data/v59.0/sobjects/Account/001Uf00000WkJ1KIAV"
          },
          "Name": "Debbie Ann Deverett",
          "Recognition_Amount_FY26__c": 10000,
          "Recognition_Amount_FY25__c": 10000,
          "JFSD_Board_Active__c": true
        },
        {
          "attributes": {
            "type": "Account",
            "url": "/services/data/v59.0/sobjects/Account/001Uf00000WkEv4IAF"
          },
          "Name": "Lisa Beth Pearl",
          "Recognition_Amount_FY26__c": 10000,
          "Recognition_Amount_FY25__c": 6000,
          "JFSD_Board_Active__c": true
        },
        {
          "attributes": {
            "type": "Account",
            "url": "/services/data/v59.0/sobjects/Account/001Uf00000WkBPQIA3"
          },
          "Name": "Ingram Losner",
          "Recognition_Amount_FY26__c": 6000,
          "Recognition_Amount_FY25__c": 5000,
          "JFSD_Board_Active__c": true
        },
        {
          "attributes": {
            "type": "Account",
            "url": "/services/data/v59.0/sobjects/Account/001Uf00000WkRMlIAN"
          },
          "Name": "Tina Beranbaum",
          "Recognition_Amount_FY26__c": 6000,
          "Recognition_Amount_FY25__c": 6780,
          "JFSD_Board_Active__c": true
        },
        {
          "attributes": {
            "type": "Account",
            "url": "/services/data/v59.0/sobjects/Account/001Uf00000WkEteIAF"
          },
          "Name": "Debbie Kornberg",
          "Recognition_Amount_FY26__c": 5400,
          "Recognition_Amount_FY25__c": 1836,
          "JFSD_Board_Active__c": true
        },
        {
          "attributes": {
            "type": "Account",
            "url": "/services/data/v59.0/sobjects/Account/001Uf00000WkQPpIAN"
          },
          "Name": "David Bark",
          "Recognition_Amount_FY26__c": 5000,
          "Recognition_Amount_FY25__c": 5000,
          "JFSD_Board_Active__c": true
        },
        {
          "attributes": {
            "type": "Account",
            "url": "/services/data/v59.0/sobjects/Account/001Uf00000WkFvDIAV"
          },
          "Name": "Robert A. Rubenstein",
          "Recognition_Amount_FY26__c": 5000,
          "Recognition_Amount_FY25__c": 50000,
          "JFSD_Board_Active__c": true
        },
        {
          "attributes": {
            "type": "Account",
            "url": "/services/data/v59.0/sobjects/Account/001Uf00000WkJngIAF"
          },
          "Name": "Larry Michael Katz",
          "Recognition_Amount_FY26__c": 5000,
          "Recognition_Amount_FY25__c": 5000,
          "JFSD_Board_Active__c": true
        },
        {
          "attributes": {
            "type": "Account",
            "url": "/services/data/v59.0/sobjects/Account/001Uf00000WkMLpIAN"
          },
          "Name": "Seth Krosner",
          "Recognition_Amount_FY26__c": 5000,
          "Recognition_Amount_FY25__c": 0,
          "JFSD_Board_Active__c": true
        },
        {
          "attributes": {
            "type": "Account",
            "url": "/services/data/v59.0/sobjects/Account/001Uf00000WkOOPIA3"
          },
          "Name": "Sarah Margaret Shekhter",
          "Recognition_Amount_FY26__c": 5000,
          "Recognition_Amount_FY25__c": 5000,
          "JFSD_Board_Active__c": true
        },
        {
          "attributes": {
            "type": "Account",
            "url": "/services/data/v59.0/sobjects/Account/001Uf00000WkOvGIAV"
          },
          "Name": "Julie Datnow",
          "Recognition_Amount_FY26__c": 5000,
          "Recognition_Amount_FY25__c": 0,
          "JFSD_Board_Active__c": true
        },
        {
          "attributes": {
            "type": "Account",
            "url": "/services/data/v59.0/sobjects/Account/001Uf00000WkGZ5IAN"
          },
          "Name": "Heather Keith",
          "Recognition_Amount_FY26__c": 4500,
          "Recognition_Amount_FY25__c": 4136,
          "JFSD_Board_Active__c": true
        },
        {
          "attributes": {
            "type": "Account",
            "url": "/services/data/v59.0/sobjects/Account/001Uf00000WkEd3IAF"
          },
          "Name": "Meryl Maneker",
          "Recognition_Amount_FY26__c": 3600,
          "Recognition_Amount_FY25__c": 3200,
          "JFSD_Board_Active__c": true
        },
        {
          "attributes": {
            "type": "Account",
            "url": "/services/data/v59.0/sobjects/Account/001Uf00000WkQSqIAN"
          },
          "Name": "Jeremy King Pearl",
          "Recognition_Amount_FY26__c": 3600,
          "Recognition_Amount_FY25__c": 3780,
          "JFSD_Board_Active__c": true
        },
        {
          "attributes": {
            "type": "Account",
            "url": "/services/data/v59.0/sobjects/Account/001Uf00000WkEDBIA3"
          },
          "Name": "Uri Feldman",
          "Recognition_Amount_FY26__c": 1980,
          "Recognition_Amount_FY25__c": 0,
          "JFSD_Board_Active__c": true
        },
        {
          "attributes": {
            "type": "Account",
            "url": "/services/data/v59.0/sobjects/Account/001Uf00000WkIfcIAF"
          },
          "Name": "Victor Shlionsky",
          "Recognition_Amount_FY26__c": 1800,
          "Recognition_Amount_FY25__c": 500,
          "JFSD_Board_Active__c": true
        },
        {
          "attributes": {
            "type": "Account",
            "url": "/services/data/v59.0/sobjects/Account/001Uf00000WkPXDIA3"
          },
          "Name": "David Bramzon",
          "Recognition_Amount_FY26__c": 1800,
          "Recognition_Amount_FY25__c": 3600,
          "JFSD_Board_Active__c": true
        },
        {
          "attributes": {
            "type": "Account",
            "url": "/services/data/v59.0/sobjects/Account/001Uf00000WkM83IAF"
          },
          "Name": "Guri A Stark",
          "Recognition_Amount_FY26__c": 1000,
          "Recognition_Amount_FY25__c": 800,
          "JFSD_Board_Active__c": true
        },
        {
          "attributes": {
            "type": "Account",
            "url": "/services/data/v59.0/sobjects/Account/001Uf00000WkBx1IAF"
          },
          "Name": "David Abraham",
          "Recognition_Amount_FY26__c": 500,
          "Recognition_Amount_FY25__c": 500,
          "JFSD_Board_Active__c": true
        },
        {
          "attributes": {
            "type": "Account",
            "url": "/services/data/v59.0/sobjects/Account/001Uf00000WkMsAIAV"
          },
          "Name": "Lisa Dawn Kornfeld",
          "Recognition_Amount_FY26__c": 0,
          "Recognition_Amount_FY25__c": 0,
          "JFSD_Board_Active__c": true
        },
        {
          "attributes": {
            "type": "Account",
            "url": "/services/data/v59.0/sobjects/Account/001Uf00000WkHeSIAV"
          },
          "Name": "Howard Bruce Somers",
          "Recognition_Amount_FY26__c": 0,
          "Recognition_Amount_FY25__c": 10000,
          "JFSD_Board_Active__c": true
        },
        {
          "attributes": {
            "type": "Account",
            "url": "/services/data/v59.0/sobjects/Account/001Uf00000WkJZZIA3"
          },
          "Name": "Elizabeth Siegler",
          "Recognition_Amount_FY26__c": 0,
          "Recognition_Amount_FY25__c": 0,
          "JFSD_Board_Active__c": true
        },
        {
          "attributes": {
            "type": "Account",
            "url": "/services/data/v59.0/sobjects/Account/001Uf00000WkMMgIAN"
          },
          "Name": "Ronit Droker",
          "Recognition_Amount_FY26__c": 0,
          "Recognition_Amount_FY25__c": 5500,
          "JFSD_Board_Active__c": true
        },
        {
          "attributes": {
            "type": "Account",
            "url": "/services/data/v59.0/sobjects/Account/001Uf00000WkHcsIAF"
          },
          "Name": "Sara Michelle Kabakoff",
          "Recognition_Amount_FY26__c": 0,
          "Recognition_Amount_FY25__c": 5500,
          "JFSD_Board_Active__c": true
        },
        {
          "attributes": {
            "type": "Account",
            "url": "/services/data/v59.0/sobjects/Account/001Uf00000WkOvPIAV"
          },
          "Name": "Shari Friedman Schenk",
          "Recognition_Amount_FY26__c": 0,
          "Recognition_Amount_FY25__c": 5000,
          "JFSD_Board_Active__c": true
        },
        {
          "attributes": {
            "type": "Account",
            "url": "/services/data/v59.0/sobjects/Account/001Uf00000WkRvhIAF"
          },
          "Name": "Elliot A Scott",
          "Recognition_Amount_FY26__c": 0,
          "Recognition_Amount_FY25__c": 32000,
          "JFSD_Board_Active__c": true
        },
        {
          "attributes": {
            "type": "Account",
            "url": "/services/data/v59.0/sobjects/Account/001Uf00000WkSAsIAN"
          },
          "Name": "Simone Abelsohn",
          "Recognition_Amount_FY26__c": 0,
          "Recognition_Amount_FY25__c": 0,
          "JFSD_Board_Active__c": true
        }
      ]
    },
    {
      "name": "Foundation Board",
      "members": []
    },
    {
      "name": "Young Adult Division",
      "members": []
    }
  ],
  "campaignSummary": {
    "raised": 185230.0,
    "participationRate": 75.8,
    "totalMembers": 33,
    "donors": 25
  },
  "givingLevels": [
    {
      "level": "$25K-$99K",
      "count": 1
    },
    {
      "level": "$10K-$24K",
      "count": 7
    },
    {
      "level": "$5K-$9K",
      "count": 9
    },
    {
      "level": "$1K-$4K",
      "count": 7
    },
    {
      "level": "Under $1K",
      "count": 9
    }
  ],
  "highlights": [],
  "kpis": {
    "boardMembers": 33,
    "participationRate": 75.8,
    "totalGiving": 185230.0
  },
  "asOfDate": "2026-03-03T07:11:29"
}