{
  "kpis": {
    "total": 198,
    "done": 10,
    "inProgress": 188
  },
  "columns": [
    "\ud83d\udfe1 In Progress",
    "\ud83d\udccb Backlog",
    "Done",
    "\u2705 Completed",
    "Notes"
  ],
  "columnLabels": {
    "\ud83d\udfe1 In Progress": "\ud83d\udfe1 In Progress",
    "\ud83d\udccb Backlog": "\ud83d\udccb Backlog",
    "Done": "Done",
    "\u2705 Completed": "\u2705 Completed",
    "Notes": "Notes"
  },
  "swimLanes": [
    "\ud83d\udfe1 In Progress",
    "\ud83d\udccb Backlog",
    "\u2705 Completed",
    "Notes",
    "Backlog: CCR Household_ID__c Backfill"
  ],
  "items": [
    {
      "title": "**Status:** \u2705 Sprint 1 Complete \u2014 18 items shipped",
      "section": "\ud83d\udfe1 In Progress",
      "done": false,
      "column": "\ud83d\udfe1 In Progress"
    },
    {
      "title": "**Location:** `projects/master-hub/`",
      "section": "\ud83d\udfe1 In Progress",
      "done": false,
      "column": "\ud83d\udfe1 In Progress"
    },
    {
      "title": "**Roadmap:** `projects/master-hub/ROADMAP.md` \u2014 Full 5-sprint plan",
      "section": "\ud83d\udfe1 In Progress",
      "done": false,
      "column": "\ud83d\udfe1 In Progress"
    },
    {
      "title": "**Sections:**",
      "section": "\ud83d\udfe1 In Progress",
      "done": false,
      "column": "\ud83d\udfe1 In Progress"
    },
    {
      "title": "**Finance** \u2014 Ramp MTD spend (live), Ramp detail dashboard (live), Budget/Cash (pending Sage)",
      "section": "\ud83d\udfe1 In Progress",
      "done": false,
      "column": "\ud83d\udfe1 In Progress"
    },
    {
      "title": "**Development** \u2014 Links to Donor Intelligence suite (live)",
      "section": "\ud83d\udfe1 In Progress",
      "done": false,
      "column": "\ud83d\udfe1 In Progress"
    },
    {
      "title": "**ScalingOps** \u2014 Data quality, advancement services ops (live)",
      "section": "\ud83d\udfe1 In Progress",
      "done": false,
      "column": "\ud83d\udfe1 In Progress"
    },
    {
      "title": "**Marketing** \u2014 Placeholder (pending HubSpot API access)",
      "section": "\ud83d\udfe1 In Progress",
      "done": false,
      "column": "\ud83d\udfe1 In Progress"
    },
    {
      "title": "**Facilities** \u2014 Links to Ecobee dashboard (live), Verkada (pending)",
      "section": "\ud83d\udfe1 In Progress",
      "done": false,
      "column": "\ud83d\udfe1 In Progress"
    },
    {
      "title": "**Features:** Phosphor icons, JFSD brand colors, definitions page, live Ramp data",
      "section": "\ud83d\udfe1 In Progress",
      "done": false,
      "column": "\ud83d\udfe1 In Progress"
    },
    {
      "title": "**Next:** HubSpot integration, Sage integration, auto-refresh scripts",
      "section": "\ud83d\udfe1 In Progress",
      "done": false,
      "column": "\ud83d\udfe1 In Progress"
    },
    {
      "title": "**Status:** \u2705 Dashboards + automated reports live",
      "section": "\ud83d\udfe1 In Progress",
      "done": false,
      "column": "\ud83d\udfe1 In Progress"
    },
    {
      "title": "**Location:** `projects/donor-intelligence/`",
      "section": "\ud83d\udfe1 In Progress",
      "done": false,
      "column": "\ud83d\udfe1 In Progress"
    },
    {
      "title": "**Dashboards:**",
      "section": "\ud83d\udfe1 In Progress",
      "done": false,
      "column": "\ud83d\udfe1 In Progress"
    },
    {
      "title": "**Hub** \u2014 Central landing page, dashboard management, freshness indicators",
      "section": "\ud83d\udfe1 In Progress",
      "done": false,
      "column": "\ud83d\udfe1 In Progress"
    },
    {
      "title": "**Daily Brief** \u2014 Proactive alerts, upcoming actions, priorities",
      "section": "\ud83d\udfe1 In Progress",
      "done": false,
      "column": "\ud83d\udfe1 In Progress"
    },
    {
      "title": "**Analytics** \u2014 Campaign progress, giving societies, retention trends",
      "section": "\ud83d\udfe1 In Progress",
      "done": false,
      "column": "\ud83d\udfe1 In Progress"
    },
    {
      "title": "**The Unasked** \u2014 Hidden gems, consistency champions, silence gap",
      "section": "\ud83d\udfe1 In Progress",
      "done": false,
      "column": "\ud83d\udfe1 In Progress"
    },
    {
      "title": "**Data Quality** \u2014 Health score, duplicates, missing info, audit findings",
      "section": "\ud83d\udfe1 In Progress",
      "done": false,
      "column": "\ud83d\udfe1 In Progress"
    },
    {
      "title": "**Pledge Management** \u2014 Aging, payment tracking, write-off risk",
      "section": "\ud83d\udfe1 In Progress",
      "done": false,
      "column": "\ud83d\udfe1 In Progress"
    },
    {
      "title": "**NEW: Automated Reports:**",
      "section": "\ud83d\udfe1 In Progress",
      "done": false,
      "column": "\ud83d\udfe1 In Progress"
    },
    {
      "title": "**Weekly Ask List** \u2014 Top 10 donors to call with suggested amounts ($49K potential)",
      "section": "\ud83d\udfe1 In Progress",
      "done": false,
      "column": "\ud83d\udfe1 In Progress"
    },
    {
      "title": "**Silence Alerts** \u2014 229 loyal donors gone quiet, $120K at risk",
      "section": "\ud83d\udfe1 In Progress",
      "done": false,
      "column": "\ud83d\udfe1 In Progress"
    },
    {
      "title": "**Cron:** Mondays 8am auto-generates and sends summary",
      "section": "\ud83d\udfe1 In Progress",
      "done": false,
      "column": "\ud83d\udfe1 In Progress"
    },
    {
      "title": "**Templates:** LYBUNT appeal, Pledge reminder, Thank you",
      "section": "\ud83d\udfe1 In Progress",
      "done": false,
      "column": "\ud83d\udfe1 In Progress"
    },
    {
      "title": "**Next:** Live Salesforce data feeds, Emma voice integration",
      "section": "\ud83d\udfe1 In Progress",
      "done": false,
      "column": "\ud83d\udfe1 In Progress"
    },
    {
      "title": "**Status:** Live with analytics",
      "section": "\ud83d\udfe1 In Progress",
      "done": false,
      "column": "\ud83d\udfe1 In Progress"
    },
    {
      "title": "**Location:** `projects/ecobee-dashboard/`",
      "section": "\ud83d\udfe1 In Progress",
      "done": false,
      "column": "\ud83d\udfe1 In Progress"
    },
    {
      "title": "**Features:**",
      "section": "\ud83d\udfe1 In Progress",
      "done": false,
      "column": "\ud83d\udfe1 In Progress"
    },
    {
      "title": "31 thermostats monitored (Federation, JCF, ADL, Common)",
      "section": "\ud83d\udfe1 In Progress",
      "done": false,
      "column": "\ud83d\udfe1 In Progress"
    },
    {
      "title": "Live temp, humidity, mode, status",
      "section": "\ud83d\udfe1 In Progress",
      "done": false,
      "column": "\ud83d\udfe1 In Progress"
    },
    {
      "title": "SQLite database for time series (6,300+ readings)",
      "section": "\ud83d\udfe1 In Progress",
      "done": false,
      "column": "\ud83d\udfe1 In Progress"
    },
    {
      "title": "Cron job every 15 minutes",
      "section": "\ud83d\udfe1 In Progress",
      "done": false,
      "column": "\ud83d\udfe1 In Progress"
    },
    {
      "title": "**NEW: Analytics dashboard** \u2014 comfort scores, anomaly detection, server room watch",
      "section": "\ud83d\udfe1 In Progress",
      "done": false,
      "column": "\ud83d\udfe1 In Progress"
    },
    {
      "title": "**API:** SmartBuildings v2 (client_credentials auth)",
      "section": "\ud83d\udfe1 In Progress",
      "done": false,
      "column": "\ud83d\udfe1 In Progress"
    },
    {
      "title": "**Findings:**",
      "section": "\ud83d\udfe1 In Progress",
      "done": false,
      "column": "\ud83d\udfe1 In Progress"
    },
    {
      "title": "Common-Server Room running HOT (76\u00b0F avg, max 77.2\u00b0F) \u2014 needs attention",
      "section": "\ud83d\udfe1 In Progress",
      "done": false,
      "column": "\ud83d\udfe1 In Progress"
    },
    {
      "title": "SWU-Oz has 18\u00b0F temp swing \u2014 unstable",
      "section": "\ud83d\udfe1 In Progress",
      "done": false,
      "column": "\ud83d\udfe1 In Progress"
    },
    {
      "title": "Building comfort score: 86/100",
      "section": "\ud83d\udfe1 In Progress",
      "done": false,
      "column": "\ud83d\udfe1 In Progress"
    },
    {
      "title": "**Next:** Historical trend analysis, predictive alerts, energy cost estimates",
      "section": "\ud83d\udfe1 In Progress",
      "done": false,
      "column": "\ud83d\udfe1 In Progress"
    },
    {
      "title": "Handbook",
      "section": "\ud83d\udccb Backlog",
      "done": false,
      "column": "\ud83d\udccb Backlog"
    },
    {
      "title": "Recruitment",
      "section": "\ud83d\udccb Backlog",
      "done": false,
      "column": "\ud83d\udccb Backlog"
    },
    {
      "title": "Onboarding",
      "section": "\ud83d\udccb Backlog",
      "done": false,
      "column": "\ud83d\udccb Backlog"
    },
    {
      "title": "Performance reviews",
      "section": "\ud83d\udccb Backlog",
      "done": false,
      "column": "\ud83d\udccb Backlog"
    },
    {
      "title": "Paylocity API exploration",
      "section": "\ud83d\udccb Backlog",
      "done": false,
      "column": "\ud83d\udccb Backlog"
    },
    {
      "title": "Ramp integration/reporting",
      "section": "\ud83d\udccb Backlog",
      "done": false,
      "column": "\ud83d\udccb Backlog"
    },
    {
      "title": "Sage integration",
      "section": "\ud83d\udccb Backlog",
      "done": false,
      "column": "\ud83d\udccb Backlog"
    },
    {
      "title": "Auditor coordination",
      "section": "\ud83d\udccb Backlog",
      "done": false,
      "column": "\ud83d\udccb Backlog"
    },
    {
      "title": "Salesforce MCP",
      "section": "\ud83d\udccb Backlog",
      "done": false,
      "column": "\ud83d\udccb Backlog"
    },
    {
      "title": "Sage MCP",
      "section": "\ud83d\udccb Backlog",
      "done": false,
      "column": "\ud83d\udccb Backlog"
    },
    {
      "title": "Slack Bots (Salesforce query)",
      "section": "\ud83d\udccb Backlog",
      "done": false,
      "column": "\ud83d\udccb Backlog"
    },
    {
      "title": "JCF roundtable prep",
      "section": "\ud83d\udccb Backlog",
      "done": false,
      "column": "\ud83d\udccb Backlog"
    },
    {
      "title": "FED roundtable prep",
      "section": "\ud83d\udccb Backlog",
      "done": false,
      "column": "\ud83d\udccb Backlog"
    },
    {
      "title": "JCF meeting packets",
      "section": "\ud83d\udccb Backlog",
      "done": false,
      "column": "\ud83d\udccb Backlog"
    },
    {
      "title": "Verkada API integration",
      "section": "\ud83d\udccb Backlog",
      "done": false,
      "column": "\ud83d\udccb Backlog"
    },
    {
      "title": "Ecobee API integration",
      "section": "\ud83d\udccb Backlog",
      "done": false,
      "column": "\ud83d\udccb Backlog"
    },
    {
      "title": "Building materials sent to Eli (2026-01-27)",
      "section": "\ud83d\udccb Backlog",
      "done": true,
      "column": "Done"
    },
    {
      "title": "Janitorial list and documentation sent to Miliah (2026-01-27)",
      "section": "\ud83d\udccb Backlog",
      "done": true,
      "column": "Done"
    },
    {
      "title": "Standard maintenance process and reporting",
      "section": "\ud83d\udccb Backlog",
      "done": false,
      "column": "\ud83d\udccb Backlog"
    },
    {
      "title": "Manage the folders",
      "section": "\ud83d\udccb Backlog",
      "done": false,
      "column": "\ud83d\udccb Backlog"
    },
    {
      "title": "Monthly schedule",
      "section": "\ud83d\udccb Backlog",
      "done": false,
      "column": "\ud83d\udccb Backlog"
    },
    {
      "title": "Policy manual and documentation",
      "section": "\ud83d\udccb Backlog",
      "done": false,
      "column": "\ud83d\udccb Backlog"
    },
    {
      "title": "Sage reports",
      "section": "\ud83d\udccb Backlog",
      "done": false,
      "column": "\ud83d\udccb Backlog"
    },
    {
      "title": "Month end close process in Numeric",
      "section": "\ud83d\udccb Backlog",
      "done": false,
      "column": "\ud83d\udccb Backlog"
    },
    {
      "title": "Updated Accounting Policy",
      "section": "\ud83d\udccb Backlog",
      "done": false,
      "column": "\ud83d\udccb Backlog"
    },
    {
      "title": "Updated spend policy",
      "section": "\ud83d\udccb Backlog",
      "done": false,
      "column": "\ud83d\udccb Backlog"
    },
    {
      "title": "Monthly reporting package and analytics",
      "section": "\ud83d\udccb Backlog",
      "done": false,
      "column": "\ud83d\udccb Backlog"
    },
    {
      "title": "**Check Scanner** \u2014 OCR scanned checks \u2192 extract donor, amount, check #, date \u2192 match Account \u2192 crea",
      "section": "\ud83d\udccb Backlog",
      "done": false,
      "column": "\ud83d\udccb Backlog"
    },
    {
      "title": "**Online Import** \u2014 Parse Excel from online giving systems \u2192 map to Salesforce fields \u2192 book with de",
      "section": "\ud83d\udccb Backlog",
      "done": false,
      "column": "\ud83d\udccb Backlog"
    },
    {
      "title": "**Challenges:** Donor name matching (fuzzy), designation mapping, review workflow",
      "section": "\ud83d\udccb Backlog",
      "done": false,
      "column": "\ud83d\udccb Backlog"
    },
    {
      "title": "**Dependencies:** Salesforce write API (confirmed working)",
      "section": "\ud83d\udccb Backlog",
      "done": false,
      "column": "\ud83d\udccb Backlog"
    },
    {
      "title": "Policies updated and integrated",
      "section": "\ud83d\udccb Backlog",
      "done": false,
      "column": "\ud83d\udccb Backlog"
    },
    {
      "title": "Gift Agreement template",
      "section": "\ud83d\udccb Backlog",
      "done": false,
      "column": "\ud83d\udccb Backlog"
    },
    {
      "title": "Acknowledgment templates",
      "section": "\ud83d\udccb Backlog",
      "done": false,
      "column": "\ud83d\udccb Backlog"
    },
    {
      "title": "Pledge reminder template",
      "section": "\ud83d\udccb Backlog",
      "done": false,
      "column": "\ud83d\udccb Backlog"
    },
    {
      "title": "**Status:** \ud83d\udfe1 In Progress",
      "section": "\ud83d\udccb Backlog",
      "done": false,
      "column": "\ud83d\udccb Backlog"
    },
    {
      "title": "**Location:** `docs/salesforce/household-greeting-system.md`",
      "section": "\ud83d\udccb Backlog",
      "done": false,
      "column": "\ud83d\udccb Backlog"
    },
    {
      "title": "**Problem:** Z\"L (deceased) households not getting correct greetings",
      "section": "\ud83d\udccb Backlog",
      "done": false,
      "column": "\ud83d\udccb Backlog"
    },
    {
      "title": "**Completed:**",
      "section": "\ud83d\udccb Backlog",
      "done": false,
      "column": "\ud83d\udccb Backlog"
    },
    {
      "title": "Full system documentation",
      "section": "\ud83d\udccb Backlog",
      "done": true,
      "column": "Done"
    },
    {
      "title": "Analyzed 99 Z\"L households",
      "section": "\ud83d\udccb Backlog",
      "done": true,
      "column": "Done"
    },
    {
      "title": "Updated 16 single-survivor greetings via API",
      "section": "\ud83d\udccb Backlog",
      "done": true,
      "column": "Done"
    },
    {
      "title": "Flow spec for Contact deceased trigger (`docs/salesforce/flow-spec-contact-deceased-trigger.md`)",
      "section": "\ud83d\udccb Backlog",
      "done": true,
      "column": "Done"
    },
    {
      "title": "**Remaining (for Paul):**",
      "section": "\ud83d\udccb Backlog",
      "done": false,
      "column": "\ud83d\udccb Backlog"
    },
    {
      "title": "Fix flow logic \u2014 handle single-survivor case (return \"FirstName LastName\" not null)",
      "section": "\ud83d\udccb Backlog",
      "done": false,
      "column": "\ud83d\udccb Backlog"
    },
    {
      "title": "Add Contact trigger \u2014 when `Deceased__c` \u2192 TRUE, update household greeting",
      "section": "\ud83d\udccb Backlog",
      "done": false,
      "column": "\ud83d\udccb Backlog"
    },
    {
      "title": "Fix double-space bug in informal greeting",
      "section": "\ud83d\udccb Backlog",
      "done": false,
      "column": "\ud83d\udccb Backlog"
    },
    {
      "title": "Data cleanup \u2014 81 Z\"L households missing relationship data",
      "section": "\ud83d\udccb Backlog",
      "done": false,
      "column": "\ud83d\udccb Backlog"
    },
    {
      "title": "**Scripts:** `scripts/zl-greeting-analysis.py`, `scripts/zl-greeting-update.js`",
      "section": "\ud83d\udccb Backlog",
      "done": false,
      "column": "\ud83d\udccb Backlog"
    },
    {
      "title": "**Problem:** Emoji icons (\ud83d\udcb0\ud83d\udcca\ud83d\udcc8\ud83d\udd04) in `AI_Research_Summary__pc` field render poorly in Excel/PDF export",
      "section": "\ud83d\udccb Backlog",
      "done": false,
      "column": "\ud83d\udccb Backlog"
    },
    {
      "title": "**Scope:** Strip or replace emojis with plain-text labels across all Person Account summaries",
      "section": "\ud83d\udccb Backlog",
      "done": false,
      "column": "\ud83d\udccb Backlog"
    },
    {
      "title": "**Source:** Prospect research pipeline consolidated summaries",
      "section": "\ud83d\udccb Backlog",
      "done": false,
      "column": "\ud83d\udccb Backlog"
    },
    {
      "title": "**Priority:** Medium \u2014 cosmetic but looks unprofessional in exports",
      "section": "\ud83d\udccb Backlog",
      "done": false,
      "column": "\ud83d\udccb Backlog"
    },
    {
      "title": "Build cleanup script (emoji \u2192 plain text headers)",
      "section": "\ud83d\udccb Backlog",
      "done": false,
      "column": "\ud83d\udccb Backlog"
    },
    {
      "title": "Run across all populated AI_Research_Summary__pc records",
      "section": "\ud83d\udccb Backlog",
      "done": false,
      "column": "\ud83d\udccb Backlog"
    }
  ],
  "asOfDate": "2026-03-06T10:20:00"
}