{
  "totalProfiled": 100,
  "capacityGap": 75841596,
  "upgradeProspects": [
    {
      "name": "Dana Zeff",
      "sf_account_id": "001Uf00000WjQAaIAN",
      "estimated_capacity": 5000000,
      "current_giving": 750000.0,
      "p2g_score": 10,
      "research_status": "champion",
      "last_updated": "2026-02-15 01:25:21"
    },
    {
      "name": "Joel Jacks",
      "sf_account_id": "001Uf00000WkF3DIAV",
      "estimated_capacity": 5000000,
      "current_giving": 0.0,
      "p2g_score": 10,
      "research_status": "lapsed_high_capacity",
      "last_updated": "2026-02-15 01:25:21"
    },
    {
      "name": "Gary D. Blake",
      "sf_account_id": "001Uf00000WkFHYIA3",
      "estimated_capacity": 5000000,
      "current_giving": 0.0,
      "p2g_score": 10,
      "research_status": "lapsed_high_capacity",
      "last_updated": "2026-02-15 01:25:21"
    },
    {
      "name": "Marsha Berkson",
      "sf_account_id": "001Uf00000WjHnmIAF",
      "estimated_capacity": 1000000,
      "current_giving": 10000.0,
      "p2g_score": 10,
      "research_status": "upgrade_candidate",
      "last_updated": "2026-02-15 01:25:21"
    },
    {
      "name": "Kay l Gurtin",
      "sf_account_id": "001Uf00000WjqxeIAB",
      "estimated_capacity": 1000000,
      "current_giving": 0.0,
      "p2g_score": 10,
      "research_status": "lapsed_high_capacity",
      "last_updated": "2026-02-15 01:25:21"
    },
    {
      "name": "Richard Greenfield",
      "sf_account_id": "001Uf00000WjsAcIAJ",
      "estimated_capacity": 1000000,
      "current_giving": 5000.0,
      "p2g_score": 10,
      "research_status": "upgrade_candidate",
      "last_updated": "2026-02-15 01:25:21"
    },
    {
      "name": "Betty and Rhonda Amber",
      "sf_account_id": "001Uf00000Wk1AoIAJ",
      "estimated_capacity": 1000000,
      "current_giving": 1800.0,
      "p2g_score": 10,
      "research_status": "upgrade_candidate",
      "last_updated": "2026-02-15 01:25:21"
    },
    {
      "name": "Daniel J. Epstein",
      "sf_account_id": "001Uf00000Wk7hGIAR",
      "estimated_capacity": 1000000,
      "current_giving": 0.0,
      "p2g_score": 10,
      "research_status": "lapsed_high_capacity",
      "last_updated": "2026-02-15 01:25:21"
    },
    {
      "name": "Phyllis F. Epstein",
      "sf_account_id": "001Uf00000Wk9uMIAR",
      "estimated_capacity": 1000000,
      "current_giving": 0.0,
      "p2g_score": 10,
      "research_status": "lapsed_high_capacity",
      "last_updated": "2026-02-15 01:25:21"
    },
    {
      "name": "Diane Feuerstein",
      "sf_account_id": "001Uf00000WkC5jIAF",
      "estimated_capacity": 1000000,
      "current_giving": 50000.0,
      "p2g_score": 10,
      "research_status": "core_donor",
      "last_updated": "2026-02-15 01:25:21"
    },
    {
      "name": "Michael Gelfand",
      "sf_account_id": "001Uf00000WkCTYIA3",
      "estimated_capacity": 1000000,
      "current_giving": 0.0,
      "p2g_score": 10,
      "research_status": "lapsed_high_capacity",
      "last_updated": "2026-02-15 01:25:21"
    },
    {
      "name": "Jerome H. Turk",
      "sf_account_id": "001Uf00000WkCm8IAF",
      "estimated_capacity": 1000000,
      "current_giving": 0.0,
      "p2g_score": 10,
      "research_status": "lapsed_high_capacity",
      "last_updated": "2026-02-15 01:25:21"
    },
    {
      "name": "Toby J. Eisenberg",
      "sf_account_id": "001Uf00000WkDLgIAN",
      "estimated_capacity": 1000000,
      "current_giving": 5000.0,
      "p2g_score": 10,
      "research_status": "upgrade_candidate",
      "last_updated": "2026-02-15 01:25:21"
    },
    {
      "name": "Helene Ziman",
      "sf_account_id": "001Uf00000WkDjKIAV",
      "estimated_capacity": 1000000,
      "current_giving": 5000.0,
      "p2g_score": 10,
      "research_status": "upgrade_candidate",
      "last_updated": "2026-02-15 01:25:21"
    },
    {
      "name": "Karen Foster Silberman",
      "sf_account_id": "001Uf00000WkFiIIAV",
      "estimated_capacity": 1000000,
      "current_giving": 60233.0,
      "p2g_score": 10,
      "research_status": "core_donor",
      "last_updated": "2026-02-15 01:25:21"
    },
    {
      "name": "Susanna Karney Flaster",
      "sf_account_id": "001Uf00000WkGpsIAF",
      "estimated_capacity": 1000000,
      "current_giving": 18000.0,
      "p2g_score": 10,
      "research_status": "upgrade_candidate",
      "last_updated": "2026-02-15 01:25:21"
    },
    {
      "name": "Frederick Schenk",
      "sf_account_id": "001Uf00000WkGtsIAF",
      "estimated_capacity": 1000000,
      "current_giving": 5000.0,
      "p2g_score": 10,
      "research_status": "upgrade_candidate",
      "last_updated": "2026-02-15 01:25:21"
    },
    {
      "name": "Irwin M. Jacobs",
      "sf_account_id": "001Uf00000WkH5gIAF",
      "estimated_capacity": 1000000,
      "current_giving": 0.0,
      "p2g_score": 10,
      "research_status": "lapsed_high_capacity",
      "last_updated": "2026-02-15 01:25:21"
    },
    {
      "name": "Cheryl I Levitt",
      "sf_account_id": "001Uf00000WkIjvIAF",
      "estimated_capacity": 1000000,
      "current_giving": 110.52,
      "p2g_score": 10,
      "research_status": "upgrade_candidate",
      "last_updated": "2026-02-15 01:25:21"
    },
    {
      "name": "Melissa Bartell",
      "sf_account_id": "001Uf00000WkIowIAF",
      "estimated_capacity": 1000000,
      "current_giving": 10000.0,
      "p2g_score": 10,
      "research_status": "upgrade_candidate",
      "last_updated": "2026-02-15 01:25:21"
    },
    {
      "name": "Ronald J. Cohn",
      "sf_account_id": "001Uf00000WkJ6SIAV",
      "estimated_capacity": 1000000,
      "current_giving": 45000.0,
      "p2g_score": 10,
      "research_status": "core_donor",
      "last_updated": "2026-02-15 01:25:21"
    },
    {
      "name": "Eileen Glasser Wesley",
      "sf_account_id": "001Uf00000WkKkNIAV",
      "estimated_capacity": 1000000,
      "current_giving": 0.0,
      "p2g_score": 10,
      "research_status": "lapsed_high_capacity",
      "last_updated": "2026-02-15 01:25:21"
    },
    {
      "name": "Jeff M. Schindler",
      "sf_account_id": "001Uf00000WkN0YIAV",
      "estimated_capacity": 1000000,
      "current_giving": 12000.0,
      "p2g_score": 10,
      "research_status": "upgrade_candidate",
      "last_updated": "2026-02-15 01:25:21"
    },
    {
      "name": "Allison Price",
      "sf_account_id": "001Uf00000WkN2hIAF",
      "estimated_capacity": 1000000,
      "current_giving": 12500.0,
      "p2g_score": 10,
      "research_status": "upgrade_candidate",
      "last_updated": "2026-02-15 01:25:21"
    },
    {
      "name": "Elliot Feuerstein",
      "sf_account_id": "001Uf00000WkNESIA3",
      "estimated_capacity": 1000000,
      "current_giving": 25000.0,
      "p2g_score": 10,
      "research_status": "upgrade_candidate",
      "last_updated": "2026-02-15 01:25:21"
    },
    {
      "name": "David Shlomo Kabakoff",
      "sf_account_id": "001Uf00000WkNfGIAV",
      "estimated_capacity": 1000000,
      "current_giving": 36000.0,
      "p2g_score": 10,
      "research_status": "core_donor",
      "last_updated": "2026-02-15 01:25:21"
    },
    {
      "name": "Susan Odenheimer Kabakoff",
      "sf_account_id": "001Uf00000WkNy2IAF",
      "estimated_capacity": 1000000,
      "current_giving": 10000.0,
      "p2g_score": 10,
      "research_status": "upgrade_candidate",
      "last_updated": "2026-02-15 01:25:21"
    },
    {
      "name": "Aaron Tal",
      "sf_account_id": "001Uf00000WjQB8IAN",
      "estimated_capacity": 1000000,
      "current_giving": 0.0,
      "p2g_score": 10,
      "research_status": null,
      "last_updated": "2026-02-15 01:25:21"
    },
    {
      "name": "Rob Mashaal",
      "sf_account_id": "001Uf00000WjyX8IAJ",
      "estimated_capacity": 1000000,
      "current_giving": 0.0,
      "p2g_score": 10,
      "research_status": null,
      "last_updated": "2026-02-15 01:25:21"
    },
    {
      "name": "Shoshana Gross",
      "sf_account_id": "001Uf00000WjhV7IAJ",
      "estimated_capacity": 1000000,
      "current_giving": 0.0,
      "p2g_score": 10,
      "research_status": null,
      "last_updated": "2026-02-15 01:25:21"
    },
    {
      "name": "Donna Gans",
      "sf_account_id": "001Uf00000WkGq5IAF",
      "estimated_capacity": 1000000,
      "current_giving": 0.0,
      "p2g_score": 10,
      "research_status": "event_to_donor",
      "last_updated": "2026-02-15 01:25:21"
    },
    {
      "name": "Marcy Schwab",
      "sf_account_id": "001Uf00000Wj0oMIAR",
      "estimated_capacity": 500000,
      "current_giving": 0.0,
      "p2g_score": 10,
      "research_status": "lapsed_high_capacity",
      "last_updated": "2026-02-15 01:25:21"
    },
    {
      "name": "Marty Weiss",
      "sf_account_id": "001Uf00000WjH6OIAV",
      "estimated_capacity": 500000,
      "current_giving": 0.0,
      "p2g_score": 10,
      "research_status": "lapsed_high_capacity",
      "last_updated": "2026-02-15 01:25:21"
    },
    {
      "name": "Linda Rauch",
      "sf_account_id": "001Uf00000WjHnjIAF",
      "estimated_capacity": 500000,
      "current_giving": 1800.0,
      "p2g_score": 10,
      "research_status": "upgrade_candidate",
      "last_updated": "2026-02-15 01:25:21"
    },
    {
      "name": "Graeme Gabriel",
      "sf_account_id": "001Uf00000WjZrnIAF",
      "estimated_capacity": 500000,
      "current_giving": 18000.0,
      "p2g_score": 10,
      "research_status": "core_donor",
      "last_updated": "2026-02-15 01:25:21"
    },
    {
      "name": "Danny Gabriel",
      "sf_account_id": "001Uf00000Wje3PIAR",
      "estimated_capacity": 500000,
      "current_giving": 0.0,
      "p2g_score": 10,
      "research_status": "lapsed_high_capacity",
      "last_updated": "2026-02-15 01:25:21"
    },
    {
      "name": "Steven Weinberg",
      "sf_account_id": "001Uf00000WjsAFIAZ",
      "estimated_capacity": 500000,
      "current_giving": 0.0,
      "p2g_score": 10,
      "research_status": "lapsed_high_capacity",
      "last_updated": "2026-02-15 01:25:21"
    },
    {
      "name": "Zita Liebermensch",
      "sf_account_id": "001Uf00000WjsANIAZ",
      "estimated_capacity": 500000,
      "current_giving": 10000.0,
      "p2g_score": 13,
      "research_status": "upgrade_candidate",
      "last_updated": "2026-02-15 01:25:21"
    },
    {
      "name": "Mark Abelkop",
      "sf_account_id": "001Uf00000Wk29hIAB",
      "estimated_capacity": 500000,
      "current_giving": 0.0,
      "p2g_score": 10,
      "research_status": "lapsed_high_capacity",
      "last_updated": "2026-02-15 01:25:21"
    },
    {
      "name": "Edward Goldberg",
      "sf_account_id": "001Uf00000WkBYLIA3",
      "estimated_capacity": 500000,
      "current_giving": 0.0,
      "p2g_score": 10,
      "research_status": "lapsed_high_capacity",
      "last_updated": "2026-02-15 01:25:21"
    },
    {
      "name": "Enrique Zagursky",
      "sf_account_id": "001Uf00000WkCbIIAV",
      "estimated_capacity": 500000,
      "current_giving": 0.0,
      "p2g_score": 10,
      "research_status": "lapsed_high_capacity",
      "last_updated": "2026-02-15 01:25:21"
    },
    {
      "name": "Nicole Gesher",
      "sf_account_id": "001Uf00000WkCbgIAF",
      "estimated_capacity": 500000,
      "current_giving": 0.0,
      "p2g_score": 10,
      "research_status": "lapsed_high_capacity",
      "last_updated": "2026-02-15 01:25:21"
    },
    {
      "name": "Phillip L. Ginsburg",
      "sf_account_id": "001Uf00000WkCoGIAV",
      "estimated_capacity": 500000,
      "current_giving": 0.0,
      "p2g_score": 10,
      "research_status": "lapsed_high_capacity",
      "last_updated": "2026-02-15 01:25:21"
    },
    {
      "name": "David Michelson",
      "sf_account_id": "001Uf00000WkD1YIAV",
      "estimated_capacity": 500000,
      "current_giving": 0.0,
      "p2g_score": 10,
      "research_status": "lapsed_high_capacity",
      "last_updated": "2026-02-15 01:25:21"
    },
    {
      "name": "Diane Saikhon Szekely",
      "sf_account_id": "001Uf00000WkDIZIA3",
      "estimated_capacity": 500000,
      "current_giving": 0.0,
      "p2g_score": 10,
      "research_status": "lapsed_high_capacity",
      "last_updated": "2026-02-15 01:25:21"
    },
    {
      "name": "STEVEN DEMETER",
      "sf_account_id": "001Uf00000WkDbGIAV",
      "estimated_capacity": 500000,
      "current_giving": 0.0,
      "p2g_score": 10,
      "research_status": "lapsed_high_capacity",
      "last_updated": "2026-02-15 01:25:21"
    },
    {
      "name": "Roberta Campbell",
      "sf_account_id": "001Uf00000WkDsmIAF",
      "estimated_capacity": 500000,
      "current_giving": 0.0,
      "p2g_score": 10,
      "research_status": "lapsed_high_capacity",
      "last_updated": "2026-02-15 01:25:21"
    },
    {
      "name": "Herbert J. Solomon",
      "sf_account_id": "001Uf00000WkDuXIAV",
      "estimated_capacity": 500000,
      "current_giving": 165000.0,
      "p2g_score": 13,
      "research_status": "champion",
      "last_updated": "2026-02-15 01:25:21"
    },
    {
      "name": "Robert Singer",
      "sf_account_id": "001Uf00000WkEDSIA3",
      "estimated_capacity": 500000,
      "current_giving": 5000.0,
      "p2g_score": 10,
      "research_status": "upgrade_candidate",
      "last_updated": "2026-02-15 01:25:21"
    },
    {
      "name": "Terry R. Klitzner",
      "sf_account_id": "001Uf00000WkEWkIAN",
      "estimated_capacity": 500000,
      "current_giving": 15000.0,
      "p2g_score": 10,
      "research_status": "core_donor",
      "last_updated": "2026-02-15 01:25:21"
    }
  ],
  "majorDonorPipeline": [
    {
      "name": "Dana Zeff",
      "sf_account_id": "001Uf00000WjQAaIAN",
      "estimated_capacity": 5000000,
      "current_giving": 750000.0,
      "p2g_score": 10,
      "research_status": "champion",
      "last_updated": "2026-02-15 01:25:21"
    },
    {
      "name": "Joel Jacks",
      "sf_account_id": "001Uf00000WkF3DIAV",
      "estimated_capacity": 5000000,
      "current_giving": 0.0,
      "p2g_score": 10,
      "research_status": "lapsed_high_capacity",
      "last_updated": "2026-02-15 01:25:21"
    },
    {
      "name": "Gary D. Blake",
      "sf_account_id": "001Uf00000WkFHYIA3",
      "estimated_capacity": 5000000,
      "current_giving": 0.0,
      "p2g_score": 10,
      "research_status": "lapsed_high_capacity",
      "last_updated": "2026-02-15 01:25:21"
    },
    {
      "name": "Marsha Berkson",
      "sf_account_id": "001Uf00000WjHnmIAF",
      "estimated_capacity": 1000000,
      "current_giving": 10000.0,
      "p2g_score": 10,
      "research_status": "upgrade_candidate",
      "last_updated": "2026-02-15 01:25:21"
    },
    {
      "name": "Kay l Gurtin",
      "sf_account_id": "001Uf00000WjqxeIAB",
      "estimated_capacity": 1000000,
      "current_giving": 0.0,
      "p2g_score": 10,
      "research_status": "lapsed_high_capacity",
      "last_updated": "2026-02-15 01:25:21"
    },
    {
      "name": "Richard Greenfield",
      "sf_account_id": "001Uf00000WjsAcIAJ",
      "estimated_capacity": 1000000,
      "current_giving": 5000.0,
      "p2g_score": 10,
      "research_status": "upgrade_candidate",
      "last_updated": "2026-02-15 01:25:21"
    },
    {
      "name": "Betty and Rhonda Amber",
      "sf_account_id": "001Uf00000Wk1AoIAJ",
      "estimated_capacity": 1000000,
      "current_giving": 1800.0,
      "p2g_score": 10,
      "research_status": "upgrade_candidate",
      "last_updated": "2026-02-15 01:25:21"
    },
    {
      "name": "Daniel J. Epstein",
      "sf_account_id": "001Uf00000Wk7hGIAR",
      "estimated_capacity": 1000000,
      "current_giving": 0.0,
      "p2g_score": 10,
      "research_status": "lapsed_high_capacity",
      "last_updated": "2026-02-15 01:25:21"
    },
    {
      "name": "Phyllis F. Epstein",
      "sf_account_id": "001Uf00000Wk9uMIAR",
      "estimated_capacity": 1000000,
      "current_giving": 0.0,
      "p2g_score": 10,
      "research_status": "lapsed_high_capacity",
      "last_updated": "2026-02-15 01:25:21"
    },
    {
      "name": "Diane Feuerstein",
      "sf_account_id": "001Uf00000WkC5jIAF",
      "estimated_capacity": 1000000,
      "current_giving": 50000.0,
      "p2g_score": 10,
      "research_status": "core_donor",
      "last_updated": "2026-02-15 01:25:21"
    },
    {
      "name": "Michael Gelfand",
      "sf_account_id": "001Uf00000WkCTYIA3",
      "estimated_capacity": 1000000,
      "current_giving": 0.0,
      "p2g_score": 10,
      "research_status": "lapsed_high_capacity",
      "last_updated": "2026-02-15 01:25:21"
    },
    {
      "name": "Jerome H. Turk",
      "sf_account_id": "001Uf00000WkCm8IAF",
      "estimated_capacity": 1000000,
      "current_giving": 0.0,
      "p2g_score": 10,
      "research_status": "lapsed_high_capacity",
      "last_updated": "2026-02-15 01:25:21"
    },
    {
      "name": "Toby J. Eisenberg",
      "sf_account_id": "001Uf00000WkDLgIAN",
      "estimated_capacity": 1000000,
      "current_giving": 5000.0,
      "p2g_score": 10,
      "research_status": "upgrade_candidate",
      "last_updated": "2026-02-15 01:25:21"
    },
    {
      "name": "Helene Ziman",
      "sf_account_id": "001Uf00000WkDjKIAV",
      "estimated_capacity": 1000000,
      "current_giving": 5000.0,
      "p2g_score": 10,
      "research_status": "upgrade_candidate",
      "last_updated": "2026-02-15 01:25:21"
    },
    {
      "name": "Karen Foster Silberman",
      "sf_account_id": "001Uf00000WkFiIIAV",
      "estimated_capacity": 1000000,
      "current_giving": 60233.0,
      "p2g_score": 10,
      "research_status": "core_donor",
      "last_updated": "2026-02-15 01:25:21"
    },
    {
      "name": "Susanna Karney Flaster",
      "sf_account_id": "001Uf00000WkGpsIAF",
      "estimated_capacity": 1000000,
      "current_giving": 18000.0,
      "p2g_score": 10,
      "research_status": "upgrade_candidate",
      "last_updated": "2026-02-15 01:25:21"
    },
    {
      "name": "Frederick Schenk",
      "sf_account_id": "001Uf00000WkGtsIAF",
      "estimated_capacity": 1000000,
      "current_giving": 5000.0,
      "p2g_score": 10,
      "research_status": "upgrade_candidate",
      "last_updated": "2026-02-15 01:25:21"
    },
    {
      "name": "Irwin M. Jacobs",
      "sf_account_id": "001Uf00000WkH5gIAF",
      "estimated_capacity": 1000000,
      "current_giving": 0.0,
      "p2g_score": 10,
      "research_status": "lapsed_high_capacity",
      "last_updated": "2026-02-15 01:25:21"
    },
    {
      "name": "Alan Viterbi",
      "sf_account_id": "001Uf00000WkIYuIAN",
      "estimated_capacity": 1000000,
      "current_giving": 500000.0,
      "p2g_score": 10,
      "research_status": "champion",
      "last_updated": "2026-02-15 01:25:21"
    },
    {
      "name": "Cheryl I Levitt",
      "sf_account_id": "001Uf00000WkIjvIAF",
      "estimated_capacity": 1000000,
      "current_giving": 110.52,
      "p2g_score": 10,
      "research_status": "upgrade_candidate",
      "last_updated": "2026-02-15 01:25:21"
    },
    {
      "name": "Melissa Bartell",
      "sf_account_id": "001Uf00000WkIowIAF",
      "estimated_capacity": 1000000,
      "current_giving": 10000.0,
      "p2g_score": 10,
      "research_status": "upgrade_candidate",
      "last_updated": "2026-02-15 01:25:21"
    },
    {
      "name": "Ronald J. Cohn",
      "sf_account_id": "001Uf00000WkJ6SIAV",
      "estimated_capacity": 1000000,
      "current_giving": 45000.0,
      "p2g_score": 10,
      "research_status": "core_donor",
      "last_updated": "2026-02-15 01:25:21"
    },
    {
      "name": "Eileen Glasser Wesley",
      "sf_account_id": "001Uf00000WkKkNIAV",
      "estimated_capacity": 1000000,
      "current_giving": 0.0,
      "p2g_score": 10,
      "research_status": "lapsed_high_capacity",
      "last_updated": "2026-02-15 01:25:21"
    },
    {
      "name": "Jeff M. Schindler",
      "sf_account_id": "001Uf00000WkN0YIAV",
      "estimated_capacity": 1000000,
      "current_giving": 12000.0,
      "p2g_score": 10,
      "research_status": "upgrade_candidate",
      "last_updated": "2026-02-15 01:25:21"
    },
    {
      "name": "Allison Price",
      "sf_account_id": "001Uf00000WkN2hIAF",
      "estimated_capacity": 1000000,
      "current_giving": 12500.0,
      "p2g_score": 10,
      "research_status": "upgrade_candidate",
      "last_updated": "2026-02-15 01:25:21"
    },
    {
      "name": "Elliot Feuerstein",
      "sf_account_id": "001Uf00000WkNESIA3",
      "estimated_capacity": 1000000,
      "current_giving": 25000.0,
      "p2g_score": 10,
      "research_status": "upgrade_candidate",
      "last_updated": "2026-02-15 01:25:21"
    },
    {
      "name": "David Shlomo Kabakoff",
      "sf_account_id": "001Uf00000WkNfGIAV",
      "estimated_capacity": 1000000,
      "current_giving": 36000.0,
      "p2g_score": 10,
      "research_status": "core_donor",
      "last_updated": "2026-02-15 01:25:21"
    },
    {
      "name": "Susan Odenheimer Kabakoff",
      "sf_account_id": "001Uf00000WkNy2IAF",
      "estimated_capacity": 1000000,
      "current_giving": 10000.0,
      "p2g_score": 10,
      "research_status": "upgrade_candidate",
      "last_updated": "2026-02-15 01:25:21"
    },
    {
      "name": "Aaron Tal",
      "sf_account_id": "001Uf00000WjQB8IAN",
      "estimated_capacity": 1000000,
      "current_giving": 0.0,
      "p2g_score": 10,
      "research_status": null,
      "last_updated": "2026-02-15 01:25:21"
    },
    {
      "name": "Rob Mashaal",
      "sf_account_id": "001Uf00000WjyX8IAJ",
      "estimated_capacity": 1000000,
      "current_giving": 0.0,
      "p2g_score": 10,
      "research_status": null,
      "last_updated": "2026-02-15 01:25:21"
    },
    {
      "name": "Shoshana Gross",
      "sf_account_id": "001Uf00000WjhV7IAJ",
      "estimated_capacity": 1000000,
      "current_giving": 0.0,
      "p2g_score": 10,
      "research_status": null,
      "last_updated": "2026-02-15 01:25:21"
    },
    {
      "name": "Donna Gans",
      "sf_account_id": "001Uf00000WkGq5IAF",
      "estimated_capacity": 1000000,
      "current_giving": 0.0,
      "p2g_score": 10,
      "research_status": "event_to_donor",
      "last_updated": "2026-02-15 01:25:21"
    },
    {
      "name": "Marcy Schwab",
      "sf_account_id": "001Uf00000Wj0oMIAR",
      "estimated_capacity": 500000,
      "current_giving": 0.0,
      "p2g_score": 10,
      "research_status": "lapsed_high_capacity",
      "last_updated": "2026-02-15 01:25:21"
    },
    {
      "name": "Marty Weiss",
      "sf_account_id": "001Uf00000WjH6OIAV",
      "estimated_capacity": 500000,
      "current_giving": 0.0,
      "p2g_score": 10,
      "research_status": "lapsed_high_capacity",
      "last_updated": "2026-02-15 01:25:21"
    },
    {
      "name": "Linda Rauch",
      "sf_account_id": "001Uf00000WjHnjIAF",
      "estimated_capacity": 500000,
      "current_giving": 1800.0,
      "p2g_score": 10,
      "research_status": "upgrade_candidate",
      "last_updated": "2026-02-15 01:25:21"
    },
    {
      "name": "Graeme Gabriel",
      "sf_account_id": "001Uf00000WjZrnIAF",
      "estimated_capacity": 500000,
      "current_giving": 18000.0,
      "p2g_score": 10,
      "research_status": "core_donor",
      "last_updated": "2026-02-15 01:25:21"
    },
    {
      "name": "Danny Gabriel",
      "sf_account_id": "001Uf00000Wje3PIAR",
      "estimated_capacity": 500000,
      "current_giving": 0.0,
      "p2g_score": 10,
      "research_status": "lapsed_high_capacity",
      "last_updated": "2026-02-15 01:25:21"
    },
    {
      "name": "Steven Weinberg",
      "sf_account_id": "001Uf00000WjsAFIAZ",
      "estimated_capacity": 500000,
      "current_giving": 0.0,
      "p2g_score": 10,
      "research_status": "lapsed_high_capacity",
      "last_updated": "2026-02-15 01:25:21"
    },
    {
      "name": "Zita Liebermensch",
      "sf_account_id": "001Uf00000WjsANIAZ",
      "estimated_capacity": 500000,
      "current_giving": 10000.0,
      "p2g_score": 13,
      "research_status": "upgrade_candidate",
      "last_updated": "2026-02-15 01:25:21"
    },
    {
      "name": "Mark Abelkop",
      "sf_account_id": "001Uf00000Wk29hIAB",
      "estimated_capacity": 500000,
      "current_giving": 0.0,
      "p2g_score": 10,
      "research_status": "lapsed_high_capacity",
      "last_updated": "2026-02-15 01:25:21"
    },
    {
      "name": "Edward Goldberg",
      "sf_account_id": "001Uf00000WkBYLIA3",
      "estimated_capacity": 500000,
      "current_giving": 0.0,
      "p2g_score": 10,
      "research_status": "lapsed_high_capacity",
      "last_updated": "2026-02-15 01:25:21"
    },
    {
      "name": "Enrique Zagursky",
      "sf_account_id": "001Uf00000WkCbIIAV",
      "estimated_capacity": 500000,
      "current_giving": 0.0,
      "p2g_score": 10,
      "research_status": "lapsed_high_capacity",
      "last_updated": "2026-02-15 01:25:21"
    },
    {
      "name": "Nicole Gesher",
      "sf_account_id": "001Uf00000WkCbgIAF",
      "estimated_capacity": 500000,
      "current_giving": 0.0,
      "p2g_score": 10,
      "research_status": "lapsed_high_capacity",
      "last_updated": "2026-02-15 01:25:21"
    },
    {
      "name": "Phillip L. Ginsburg",
      "sf_account_id": "001Uf00000WkCoGIAV",
      "estimated_capacity": 500000,
      "current_giving": 0.0,
      "p2g_score": 10,
      "research_status": "lapsed_high_capacity",
      "last_updated": "2026-02-15 01:25:21"
    },
    {
      "name": "David Michelson",
      "sf_account_id": "001Uf00000WkD1YIAV",
      "estimated_capacity": 500000,
      "current_giving": 0.0,
      "p2g_score": 10,
      "research_status": "lapsed_high_capacity",
      "last_updated": "2026-02-15 01:25:21"
    },
    {
      "name": "Diane Saikhon Szekely",
      "sf_account_id": "001Uf00000WkDIZIA3",
      "estimated_capacity": 500000,
      "current_giving": 0.0,
      "p2g_score": 10,
      "research_status": "lapsed_high_capacity",
      "last_updated": "2026-02-15 01:25:21"
    },
    {
      "name": "STEVEN DEMETER",
      "sf_account_id": "001Uf00000WkDbGIAV",
      "estimated_capacity": 500000,
      "current_giving": 0.0,
      "p2g_score": 10,
      "research_status": "lapsed_high_capacity",
      "last_updated": "2026-02-15 01:25:21"
    }
  ],
  "givingVsCapacity": [
    {
      "bucket": "10-25%",
      "count": 3
    },
    {
      "bucket": "0-10%",
      "count": 95
    },
    {
      "bucket": "50-75%",
      "count": 1
    },
    {
      "bucket": "25-50%",
      "count": 1
    }
  ],
  "trajectoryAnalysis": [
    {
      "name": "Dana Zeff",
      "sf_account_id": "001Uf00000WjQAaIAN",
      "estimated_capacity": 5000000,
      "current_giving": 750000.0,
      "p2g_score": 10,
      "research_status": "champion",
      "last_updated": "2026-02-15 01:25:21"
    },
    {
      "name": "Joel Jacks",
      "sf_account_id": "001Uf00000WkF3DIAV",
      "estimated_capacity": 5000000,
      "current_giving": 0.0,
      "p2g_score": 10,
      "research_status": "lapsed_high_capacity",
      "last_updated": "2026-02-15 01:25:21"
    },
    {
      "name": "Gary D. Blake",
      "sf_account_id": "001Uf00000WkFHYIA3",
      "estimated_capacity": 5000000,
      "current_giving": 0.0,
      "p2g_score": 10,
      "research_status": "lapsed_high_capacity",
      "last_updated": "2026-02-15 01:25:21"
    },
    {
      "name": "Marsha Berkson",
      "sf_account_id": "001Uf00000WjHnmIAF",
      "estimated_capacity": 1000000,
      "current_giving": 10000.0,
      "p2g_score": 10,
      "research_status": "upgrade_candidate",
      "last_updated": "2026-02-15 01:25:21"
    },
    {
      "name": "Kay l Gurtin",
      "sf_account_id": "001Uf00000WjqxeIAB",
      "estimated_capacity": 1000000,
      "current_giving": 0.0,
      "p2g_score": 10,
      "research_status": "lapsed_high_capacity",
      "last_updated": "2026-02-15 01:25:21"
    },
    {
      "name": "Richard Greenfield",
      "sf_account_id": "001Uf00000WjsAcIAJ",
      "estimated_capacity": 1000000,
      "current_giving": 5000.0,
      "p2g_score": 10,
      "research_status": "upgrade_candidate",
      "last_updated": "2026-02-15 01:25:21"
    },
    {
      "name": "Betty and Rhonda Amber",
      "sf_account_id": "001Uf00000Wk1AoIAJ",
      "estimated_capacity": 1000000,
      "current_giving": 1800.0,
      "p2g_score": 10,
      "research_status": "upgrade_candidate",
      "last_updated": "2026-02-15 01:25:21"
    },
    {
      "name": "Daniel J. Epstein",
      "sf_account_id": "001Uf00000Wk7hGIAR",
      "estimated_capacity": 1000000,
      "current_giving": 0.0,
      "p2g_score": 10,
      "research_status": "lapsed_high_capacity",
      "last_updated": "2026-02-15 01:25:21"
    },
    {
      "name": "Phyllis F. Epstein",
      "sf_account_id": "001Uf00000Wk9uMIAR",
      "estimated_capacity": 1000000,
      "current_giving": 0.0,
      "p2g_score": 10,
      "research_status": "lapsed_high_capacity",
      "last_updated": "2026-02-15 01:25:21"
    },
    {
      "name": "Diane Feuerstein",
      "sf_account_id": "001Uf00000WkC5jIAF",
      "estimated_capacity": 1000000,
      "current_giving": 50000.0,
      "p2g_score": 10,
      "research_status": "core_donor",
      "last_updated": "2026-02-15 01:25:21"
    },
    {
      "name": "Michael Gelfand",
      "sf_account_id": "001Uf00000WkCTYIA3",
      "estimated_capacity": 1000000,
      "current_giving": 0.0,
      "p2g_score": 10,
      "research_status": "lapsed_high_capacity",
      "last_updated": "2026-02-15 01:25:21"
    },
    {
      "name": "Jerome H. Turk",
      "sf_account_id": "001Uf00000WkCm8IAF",
      "estimated_capacity": 1000000,
      "current_giving": 0.0,
      "p2g_score": 10,
      "research_status": "lapsed_high_capacity",
      "last_updated": "2026-02-15 01:25:21"
    },
    {
      "name": "Toby J. Eisenberg",
      "sf_account_id": "001Uf00000WkDLgIAN",
      "estimated_capacity": 1000000,
      "current_giving": 5000.0,
      "p2g_score": 10,
      "research_status": "upgrade_candidate",
      "last_updated": "2026-02-15 01:25:21"
    },
    {
      "name": "Helene Ziman",
      "sf_account_id": "001Uf00000WkDjKIAV",
      "estimated_capacity": 1000000,
      "current_giving": 5000.0,
      "p2g_score": 10,
      "research_status": "upgrade_candidate",
      "last_updated": "2026-02-15 01:25:21"
    },
    {
      "name": "Karen Foster Silberman",
      "sf_account_id": "001Uf00000WkFiIIAV",
      "estimated_capacity": 1000000,
      "current_giving": 60233.0,
      "p2g_score": 10,
      "research_status": "core_donor",
      "last_updated": "2026-02-15 01:25:21"
    },
    {
      "name": "Susanna Karney Flaster",
      "sf_account_id": "001Uf00000WkGpsIAF",
      "estimated_capacity": 1000000,
      "current_giving": 18000.0,
      "p2g_score": 10,
      "research_status": "upgrade_candidate",
      "last_updated": "2026-02-15 01:25:21"
    },
    {
      "name": "Frederick Schenk",
      "sf_account_id": "001Uf00000WkGtsIAF",
      "estimated_capacity": 1000000,
      "current_giving": 5000.0,
      "p2g_score": 10,
      "research_status": "upgrade_candidate",
      "last_updated": "2026-02-15 01:25:21"
    },
    {
      "name": "Irwin M. Jacobs",
      "sf_account_id": "001Uf00000WkH5gIAF",
      "estimated_capacity": 1000000,
      "current_giving": 0.0,
      "p2g_score": 10,
      "research_status": "lapsed_high_capacity",
      "last_updated": "2026-02-15 01:25:21"
    },
    {
      "name": "Alan Viterbi",
      "sf_account_id": "001Uf00000WkIYuIAN",
      "estimated_capacity": 1000000,
      "current_giving": 500000.0,
      "p2g_score": 10,
      "research_status": "champion",
      "last_updated": "2026-02-15 01:25:21"
    },
    {
      "name": "Cheryl I Levitt",
      "sf_account_id": "001Uf00000WkIjvIAF",
      "estimated_capacity": 1000000,
      "current_giving": 110.52,
      "p2g_score": 10,
      "research_status": "upgrade_candidate",
      "last_updated": "2026-02-15 01:25:21"
    },
    {
      "name": "Melissa Bartell",
      "sf_account_id": "001Uf00000WkIowIAF",
      "estimated_capacity": 1000000,
      "current_giving": 10000.0,
      "p2g_score": 10,
      "research_status": "upgrade_candidate",
      "last_updated": "2026-02-15 01:25:21"
    },
    {
      "name": "Ronald J. Cohn",
      "sf_account_id": "001Uf00000WkJ6SIAV",
      "estimated_capacity": 1000000,
      "current_giving": 45000.0,
      "p2g_score": 10,
      "research_status": "core_donor",
      "last_updated": "2026-02-15 01:25:21"
    },
    {
      "name": "Eileen Glasser Wesley",
      "sf_account_id": "001Uf00000WkKkNIAV",
      "estimated_capacity": 1000000,
      "current_giving": 0.0,
      "p2g_score": 10,
      "research_status": "lapsed_high_capacity",
      "last_updated": "2026-02-15 01:25:21"
    },
    {
      "name": "Jeff M. Schindler",
      "sf_account_id": "001Uf00000WkN0YIAV",
      "estimated_capacity": 1000000,
      "current_giving": 12000.0,
      "p2g_score": 10,
      "research_status": "upgrade_candidate",
      "last_updated": "2026-02-15 01:25:21"
    },
    {
      "name": "Allison Price",
      "sf_account_id": "001Uf00000WkN2hIAF",
      "estimated_capacity": 1000000,
      "current_giving": 12500.0,
      "p2g_score": 10,
      "research_status": "upgrade_candidate",
      "last_updated": "2026-02-15 01:25:21"
    },
    {
      "name": "Elliot Feuerstein",
      "sf_account_id": "001Uf00000WkNESIA3",
      "estimated_capacity": 1000000,
      "current_giving": 25000.0,
      "p2g_score": 10,
      "research_status": "upgrade_candidate",
      "last_updated": "2026-02-15 01:25:21"
    },
    {
      "name": "David Shlomo Kabakoff",
      "sf_account_id": "001Uf00000WkNfGIAV",
      "estimated_capacity": 1000000,
      "current_giving": 36000.0,
      "p2g_score": 10,
      "research_status": "core_donor",
      "last_updated": "2026-02-15 01:25:21"
    },
    {
      "name": "Susan Odenheimer Kabakoff",
      "sf_account_id": "001Uf00000WkNy2IAF",
      "estimated_capacity": 1000000,
      "current_giving": 10000.0,
      "p2g_score": 10,
      "research_status": "upgrade_candidate",
      "last_updated": "2026-02-15 01:25:21"
    },
    {
      "name": "Aaron Tal",
      "sf_account_id": "001Uf00000WjQB8IAN",
      "estimated_capacity": 1000000,
      "current_giving": 0.0,
      "p2g_score": 10,
      "research_status": null,
      "last_updated": "2026-02-15 01:25:21"
    },
    {
      "name": "Rob Mashaal",
      "sf_account_id": "001Uf00000WjyX8IAJ",
      "estimated_capacity": 1000000,
      "current_giving": 0.0,
      "p2g_score": 10,
      "research_status": null,
      "last_updated": "2026-02-15 01:25:21"
    },
    {
      "name": "Shoshana Gross",
      "sf_account_id": "001Uf00000WjhV7IAJ",
      "estimated_capacity": 1000000,
      "current_giving": 0.0,
      "p2g_score": 10,
      "research_status": null,
      "last_updated": "2026-02-15 01:25:21"
    },
    {
      "name": "Donna Gans",
      "sf_account_id": "001Uf00000WkGq5IAF",
      "estimated_capacity": 1000000,
      "current_giving": 0.0,
      "p2g_score": 10,
      "research_status": "event_to_donor",
      "last_updated": "2026-02-15 01:25:21"
    },
    {
      "name": "Marcy Schwab",
      "sf_account_id": "001Uf00000Wj0oMIAR",
      "estimated_capacity": 500000,
      "current_giving": 0.0,
      "p2g_score": 10,
      "research_status": "lapsed_high_capacity",
      "last_updated": "2026-02-15 01:25:21"
    },
    {
      "name": "Marty Weiss",
      "sf_account_id": "001Uf00000WjH6OIAV",
      "estimated_capacity": 500000,
      "current_giving": 0.0,
      "p2g_score": 10,
      "research_status": "lapsed_high_capacity",
      "last_updated": "2026-02-15 01:25:21"
    },
    {
      "name": "Linda Rauch",
      "sf_account_id": "001Uf00000WjHnjIAF",
      "estimated_capacity": 500000,
      "current_giving": 1800.0,
      "p2g_score": 10,
      "research_status": "upgrade_candidate",
      "last_updated": "2026-02-15 01:25:21"
    },
    {
      "name": "Graeme Gabriel",
      "sf_account_id": "001Uf00000WjZrnIAF",
      "estimated_capacity": 500000,
      "current_giving": 18000.0,
      "p2g_score": 10,
      "research_status": "core_donor",
      "last_updated": "2026-02-15 01:25:21"
    },
    {
      "name": "Danny Gabriel",
      "sf_account_id": "001Uf00000Wje3PIAR",
      "estimated_capacity": 500000,
      "current_giving": 0.0,
      "p2g_score": 10,
      "research_status": "lapsed_high_capacity",
      "last_updated": "2026-02-15 01:25:21"
    },
    {
      "name": "Steven Weinberg",
      "sf_account_id": "001Uf00000WjsAFIAZ",
      "estimated_capacity": 500000,
      "current_giving": 0.0,
      "p2g_score": 10,
      "research_status": "lapsed_high_capacity",
      "last_updated": "2026-02-15 01:25:21"
    },
    {
      "name": "Zita Liebermensch",
      "sf_account_id": "001Uf00000WjsANIAZ",
      "estimated_capacity": 500000,
      "current_giving": 10000.0,
      "p2g_score": 13,
      "research_status": "upgrade_candidate",
      "last_updated": "2026-02-15 01:25:21"
    },
    {
      "name": "Mark Abelkop",
      "sf_account_id": "001Uf00000Wk29hIAB",
      "estimated_capacity": 500000,
      "current_giving": 0.0,
      "p2g_score": 10,
      "research_status": "lapsed_high_capacity",
      "last_updated": "2026-02-15 01:25:21"
    },
    {
      "name": "Edward Goldberg",
      "sf_account_id": "001Uf00000WkBYLIA3",
      "estimated_capacity": 500000,
      "current_giving": 0.0,
      "p2g_score": 10,
      "research_status": "lapsed_high_capacity",
      "last_updated": "2026-02-15 01:25:21"
    },
    {
      "name": "Enrique Zagursky",
      "sf_account_id": "001Uf00000WkCbIIAV",
      "estimated_capacity": 500000,
      "current_giving": 0.0,
      "p2g_score": 10,
      "research_status": "lapsed_high_capacity",
      "last_updated": "2026-02-15 01:25:21"
    },
    {
      "name": "Nicole Gesher",
      "sf_account_id": "001Uf00000WkCbgIAF",
      "estimated_capacity": 500000,
      "current_giving": 0.0,
      "p2g_score": 10,
      "research_status": "lapsed_high_capacity",
      "last_updated": "2026-02-15 01:25:21"
    },
    {
      "name": "Phillip L. Ginsburg",
      "sf_account_id": "001Uf00000WkCoGIAV",
      "estimated_capacity": 500000,
      "current_giving": 0.0,
      "p2g_score": 10,
      "research_status": "lapsed_high_capacity",
      "last_updated": "2026-02-15 01:25:21"
    },
    {
      "name": "David Michelson",
      "sf_account_id": "001Uf00000WkD1YIAV",
      "estimated_capacity": 500000,
      "current_giving": 0.0,
      "p2g_score": 10,
      "research_status": "lapsed_high_capacity",
      "last_updated": "2026-02-15 01:25:21"
    },
    {
      "name": "Diane Saikhon Szekely",
      "sf_account_id": "001Uf00000WkDIZIA3",
      "estimated_capacity": 500000,
      "current_giving": 0.0,
      "p2g_score": 10,
      "research_status": "lapsed_high_capacity",
      "last_updated": "2026-02-15 01:25:21"
    },
    {
      "name": "STEVEN DEMETER",
      "sf_account_id": "001Uf00000WkDbGIAV",
      "estimated_capacity": 500000,
      "current_giving": 0.0,
      "p2g_score": 10,
      "research_status": "lapsed_high_capacity",
      "last_updated": "2026-02-15 01:25:21"
    },
    {
      "name": "Roberta Campbell",
      "sf_account_id": "001Uf00000WkDsmIAF",
      "estimated_capacity": 500000,
      "current_giving": 0.0,
      "p2g_score": 10,
      "research_status": "lapsed_high_capacity",
      "last_updated": "2026-02-15 01:25:21"
    },
    {
      "name": "Herbert J. Solomon",
      "sf_account_id": "001Uf00000WkDuXIAV",
      "estimated_capacity": 500000,
      "current_giving": 165000.0,
      "p2g_score": 13,
      "research_status": "champion",
      "last_updated": "2026-02-15 01:25:21"
    },
    {
      "name": "Robert Singer",
      "sf_account_id": "001Uf00000WkEDSIA3",
      "estimated_capacity": 500000,
      "current_giving": 5000.0,
      "p2g_score": 10,
      "research_status": "upgrade_candidate",
      "last_updated": "2026-02-15 01:25:21"
    },
    {
      "name": "Terry R. Klitzner",
      "sf_account_id": "001Uf00000WkEWkIAN",
      "estimated_capacity": 500000,
      "current_giving": 15000.0,
      "p2g_score": 10,
      "research_status": "core_donor",
      "last_updated": "2026-02-15 01:25:21"
    },
    {
      "name": "Phyllis Harris",
      "sf_account_id": "001Uf00000WkEz6IAF",
      "estimated_capacity": 500000,
      "current_giving": 7500.0,
      "p2g_score": 10,
      "research_status": "upgrade_candidate",
      "last_updated": "2026-02-15 01:25:21"
    },
    {
      "name": "Lara Woolf Grusd",
      "sf_account_id": "001Uf00000WkF06IAF",
      "estimated_capacity": 500000,
      "current_giving": 5210.3,
      "p2g_score": 10,
      "research_status": "upgrade_candidate",
      "last_updated": "2026-02-15 01:25:21"
    },
    {
      "name": "Andrew Garman",
      "sf_account_id": "001Uf00000WkF3JIAV",
      "estimated_capacity": 500000,
      "current_giving": 36000.0,
      "p2g_score": 10,
      "research_status": "board_overlap",
      "last_updated": "2026-02-15 01:25:21"
    },
    {
      "name": "Susan Rachelle Chortek Weisman",
      "sf_account_id": "001Uf00000WkF4ZIAV",
      "estimated_capacity": 500000,
      "current_giving": 110000.0,
      "p2g_score": 10,
      "research_status": "champion",
      "last_updated": "2026-02-15 01:25:21"
    },
    {
      "name": "Alan Robert Saltiel",
      "sf_account_id": "001Uf00000WkF8CIAV",
      "estimated_capacity": 500000,
      "current_giving": 5000.0,
      "p2g_score": 10,
      "research_status": "upgrade_candidate",
      "last_updated": "2026-02-15 01:25:21"
    },
    {
      "name": "Susan Shmalo",
      "sf_account_id": "001Uf00000WkFSKIA3",
      "estimated_capacity": 500000,
      "current_giving": 5000.0,
      "p2g_score": 10,
      "research_status": "upgrade_candidate",
      "last_updated": "2026-02-15 01:25:21"
    },
    {
      "name": "Gary Evan Jacobs",
      "sf_account_id": "001Uf00000WkFXmIAN",
      "estimated_capacity": 500000,
      "current_giving": 80000.0,
      "p2g_score": 13,
      "research_status": "champion",
      "last_updated": "2026-02-15 01:25:21"
    },
    {
      "name": "Kenneth D. Polin",
      "sf_account_id": "001Uf00000WkFhbIAF",
      "estimated_capacity": 500000,
      "current_giving": 0.0,
      "p2g_score": 10,
      "research_status": "lapsed_high_capacity",
      "last_updated": "2026-02-15 01:25:21"
    },
    {
      "name": "Robert A. Rubenstein",
      "sf_account_id": "001Uf00000WkFvDIAV",
      "estimated_capacity": 500000,
      "current_giving": 5000.0,
      "p2g_score": 10,
      "research_status": "upgrade_candidate",
      "last_updated": "2026-02-15 01:25:21"
    },
    {
      "name": "Anne Nagorner",
      "sf_account_id": "001Uf00000WkG0vIAF",
      "estimated_capacity": 500000,
      "current_giving": 0.0,
      "p2g_score": 10,
      "research_status": "lapsed_high_capacity",
      "last_updated": "2026-02-15 01:25:21"
    },
    {
      "name": "Ellen Epsten Benkle",
      "sf_account_id": "001Uf00000WkG4VIAV",
      "estimated_capacity": 500000,
      "current_giving": 0.0,
      "p2g_score": 10,
      "research_status": "lapsed_high_capacity",
      "last_updated": "2026-02-15 01:25:21"
    },
    {
      "name": "Mona S. Platt",
      "sf_account_id": "001Uf00000WkGXlIAN",
      "estimated_capacity": 500000,
      "current_giving": 0.0,
      "p2g_score": 10,
      "research_status": "lapsed_high_capacity",
      "last_updated": "2026-02-15 01:25:21"
    },
    {
      "name": "Heather Keith",
      "sf_account_id": "001Uf00000WkGZ5IAN",
      "estimated_capacity": 500000,
      "current_giving": 4500.0,
      "p2g_score": 10,
      "research_status": "upgrade_candidate",
      "last_updated": "2026-02-15 01:25:21"
    },
    {
      "name": "Thomas Elden",
      "sf_account_id": "001Uf00000WkGZNIA3",
      "estimated_capacity": 500000,
      "current_giving": 0.0,
      "p2g_score": 10,
      "research_status": "lapsed_high_capacity",
      "last_updated": "2026-02-15 01:25:21"
    },
    {
      "name": "Allegra Clegg",
      "sf_account_id": "001Uf00000WkH3SIAV",
      "estimated_capacity": 500000,
      "current_giving": 5000.0,
      "p2g_score": 10,
      "research_status": "upgrade_candidate",
      "last_updated": "2026-02-15 01:25:21"
    },
    {
      "name": "Mary Ann Scher",
      "sf_account_id": "001Uf00000WkHDFIA3",
      "estimated_capacity": 500000,
      "current_giving": 0.0,
      "p2g_score": 10,
      "research_status": "lapsed_high_capacity",
      "last_updated": "2026-02-15 01:25:21"
    },
    {
      "name": "Gillian Vapnek",
      "sf_account_id": "001Uf00000WkHbhIAF",
      "estimated_capacity": 500000,
      "current_giving": 4500.0,
      "p2g_score": 10,
      "research_status": "upgrade_candidate",
      "last_updated": "2026-02-15 01:25:21"
    },
    {
      "name": "Judith L. Amster",
      "sf_account_id": "001Uf00000WkHgFIAV",
      "estimated_capacity": 500000,
      "current_giving": 0.0,
      "p2g_score": 10,
      "research_status": "lapsed_high_capacity",
      "last_updated": "2026-02-15 01:25:21"
    },
    {
      "name": "Colin Seid",
      "sf_account_id": "001Uf00000WkI1gIAF",
      "estimated_capacity": 500000,
      "current_giving": 0.0,
      "p2g_score": 10,
      "research_status": "lapsed_high_capacity",
      "last_updated": "2026-02-15 01:25:21"
    },
    {
      "name": "Jack Maizel",
      "sf_account_id": "001Uf00000WkI6dIAF",
      "estimated_capacity": 500000,
      "current_giving": 10250.0,
      "p2g_score": 10,
      "research_status": "upgrade_candidate",
      "last_updated": "2026-02-15 01:25:21"
    },
    {
      "name": "Gregg Kornfeld",
      "sf_account_id": "001Uf00000WkIERIA3",
      "estimated_capacity": 500000,
      "current_giving": 0.0,
      "p2g_score": 10,
      "research_status": "lapsed_high_capacity",
      "last_updated": "2026-02-15 01:25:21"
    },
    {
      "name": "Jane Ellen Fantel",
      "sf_account_id": "001Uf00000WkJeZIAV",
      "estimated_capacity": 500000,
      "current_giving": 0.0,
      "p2g_score": 10,
      "research_status": "lapsed_high_capacity",
      "last_updated": "2026-02-15 01:25:21"
    },
    {
      "name": "Robert Kucinski",
      "sf_account_id": "001Uf00000WkJjXIAV",
      "estimated_capacity": 500000,
      "current_giving": 0.0,
      "p2g_score": 10,
      "research_status": "lapsed_high_capacity",
      "last_updated": "2026-02-15 01:25:21"
    },
    {
      "name": "Larry Michael Katz",
      "sf_account_id": "001Uf00000WkJngIAF",
      "estimated_capacity": 500000,
      "current_giving": 5000.0,
      "p2g_score": 10,
      "research_status": "upgrade_candidate",
      "last_updated": "2026-02-15 01:25:21"
    },
    {
      "name": "Jeremy Berg",
      "sf_account_id": "001Uf00000WkJuqIAF",
      "estimated_capacity": 500000,
      "current_giving": 10000.0,
      "p2g_score": 23,
      "research_status": "upgrade_candidate",
      "last_updated": "2026-02-15 01:25:21"
    },
    {
      "name": "Laurie Hoshaw",
      "sf_account_id": "001Uf00000WkKLoIAN",
      "estimated_capacity": 500000,
      "current_giving": 0.0,
      "p2g_score": 10,
      "research_status": "lapsed_high_capacity",
      "last_updated": "2026-02-15 01:25:21"
    },
    {
      "name": "Lisa Foster",
      "sf_account_id": "001Uf00000WkKk3IAF",
      "estimated_capacity": 500000,
      "current_giving": 0.0,
      "p2g_score": 10,
      "research_status": "lapsed_high_capacity",
      "last_updated": "2026-02-15 01:25:21"
    },
    {
      "name": "Andrew M. Glatt",
      "sf_account_id": "001Uf00000WkLHCIA3",
      "estimated_capacity": 500000,
      "current_giving": 5000.0,
      "p2g_score": 10,
      "research_status": "upgrade_candidate",
      "last_updated": "2026-02-15 01:25:21"
    },
    {
      "name": "Julie Litman",
      "sf_account_id": "001Uf00000WkLWdIAN",
      "estimated_capacity": 500000,
      "current_giving": 0.0,
      "p2g_score": 10,
      "research_status": "lapsed_high_capacity",
      "last_updated": "2026-02-15 01:25:21"
    },
    {
      "name": "Esther Fischer",
      "sf_account_id": "001Uf00000WkM7TIAV",
      "estimated_capacity": 500000,
      "current_giving": 35000.0,
      "p2g_score": 10,
      "research_status": "core_donor",
      "last_updated": "2026-02-15 01:25:21"
    },
    {
      "name": "Harvey L. Amster",
      "sf_account_id": "001Uf00000WkMI7IAN",
      "estimated_capacity": 500000,
      "current_giving": 0.0,
      "p2g_score": 10,
      "research_status": "lapsed_high_capacity",
      "last_updated": "2026-02-15 01:25:21"
    },
    {
      "name": "Allan Ziman",
      "sf_account_id": "001Uf00000WkMO8IAN",
      "estimated_capacity": 500000,
      "current_giving": 5000.0,
      "p2g_score": 10,
      "research_status": "upgrade_candidate",
      "last_updated": "2026-02-15 01:25:21"
    },
    {
      "name": "Ira Cohen",
      "sf_account_id": "001Uf00000WkMPMIA3",
      "estimated_capacity": 500000,
      "current_giving": 20000.0,
      "p2g_score": 10,
      "research_status": "core_donor",
      "last_updated": "2026-02-15 01:25:21"
    },
    {
      "name": "Andrew M. Ratner",
      "sf_account_id": "001Uf00000WkMQpIAN",
      "estimated_capacity": 500000,
      "current_giving": 0.0,
      "p2g_score": 10,
      "research_status": "lapsed_high_capacity",
      "last_updated": "2026-02-15 01:25:21"
    },
    {
      "name": "Sheryl J. Kaufman",
      "sf_account_id": "001Uf00000WkMWJIA3",
      "estimated_capacity": 500000,
      "current_giving": 25000.0,
      "p2g_score": 13,
      "research_status": "core_donor",
      "last_updated": "2026-02-15 01:25:21"
    },
    {
      "name": "Darryl Hall",
      "sf_account_id": "001Uf00000WkN4sIAF",
      "estimated_capacity": 500000,
      "current_giving": 0.0,
      "p2g_score": 10,
      "research_status": "lapsed_high_capacity",
      "last_updated": "2026-02-15 01:25:21"
    },
    {
      "name": "Raymond I. Fink",
      "sf_account_id": "001Uf00000WkN6NIAV",
      "estimated_capacity": 500000,
      "current_giving": 0.0,
      "p2g_score": 10,
      "research_status": "lapsed_high_capacity",
      "last_updated": "2026-02-15 01:25:21"
    },
    {
      "name": "Merrill Haimsohn",
      "sf_account_id": "001Uf00000WjHntIAF",
      "estimated_capacity": 500000,
      "current_giving": 0.0,
      "p2g_score": 10,
      "research_status": "event_to_donor",
      "last_updated": "2026-02-15 01:25:21"
    },
    {
      "name": "Philip Jochelson",
      "sf_account_id": "001Uf00000WjHoSIAV",
      "estimated_capacity": 500000,
      "current_giving": 0.0,
      "p2g_score": 10,
      "research_status": "event_to_donor",
      "last_updated": "2026-02-15 01:25:21"
    },
    {
      "name": "David Kleinfeld",
      "sf_account_id": "001Uf00000Wjh5vIAB",
      "estimated_capacity": 500000,
      "current_giving": 0.0,
      "p2g_score": 10,
      "research_status": "event_to_donor",
      "last_updated": "2026-02-15 01:25:21"
    },
    {
      "name": "Marcelle Bayley",
      "sf_account_id": "001Uf00000Wjh6IIAR",
      "estimated_capacity": 500000,
      "current_giving": 0.0,
      "p2g_score": 10,
      "research_status": "event_to_donor",
      "last_updated": "2026-02-15 01:25:21"
    },
    {
      "name": "Andrew Serwin",
      "sf_account_id": "001Uf00000Wj0p5IAB",
      "estimated_capacity": 500000,
      "current_giving": 0.0,
      "p2g_score": 10,
      "research_status": "event_to_donor",
      "last_updated": "2026-02-15 01:25:21"
    },
    {
      "name": "Mara Goverman",
      "sf_account_id": "001Uf00000WkBRGIA3",
      "estimated_capacity": 500000,
      "current_giving": 0.0,
      "p2g_score": 10,
      "research_status": null,
      "last_updated": "2026-02-15 01:25:21"
    },
    {
      "name": "Judith Perlman",
      "sf_account_id": "001Uf00000WjZBDIA3",
      "estimated_capacity": 500000,
      "current_giving": 0.0,
      "p2g_score": 23,
      "research_status": "event_to_donor",
      "last_updated": "2026-02-15 01:25:21"
    },
    {
      "name": "Nancy Wolman",
      "sf_account_id": "001Uf00000WjZBjIAN",
      "estimated_capacity": 500000,
      "current_giving": 0.0,
      "p2g_score": 10,
      "research_status": "event_to_donor",
      "last_updated": "2026-02-15 01:25:21"
    },
    {
      "name": "Russel M Steingold",
      "sf_account_id": "001Uf00000WjZC4IAN",
      "estimated_capacity": 500000,
      "current_giving": 0.0,
      "p2g_score": 10,
      "research_status": null,
      "last_updated": "2026-02-15 01:25:21"
    },
    {
      "name": "David Paul Leib",
      "sf_account_id": "001Uf00000WjsAnIAJ",
      "estimated_capacity": 500000,
      "current_giving": 0.0,
      "p2g_score": 10,
      "research_status": "event_to_donor",
      "last_updated": "2026-02-15 01:25:21"
    },
    {
      "name": "Colette Royston",
      "sf_account_id": "001Uf00000Wjys7IAB",
      "estimated_capacity": 500000,
      "current_giving": 0.0,
      "p2g_score": 13,
      "research_status": null,
      "last_updated": "2026-02-15 01:25:21"
    },
    {
      "name": "Sandra Sacks",
      "sf_account_id": "001Uf00000WjysNIAR",
      "estimated_capacity": 500000,
      "current_giving": 0.0,
      "p2g_score": 10,
      "research_status": "event_to_donor",
      "last_updated": "2026-02-15 01:25:21"
    }
  ],
  "kpis": {
    "totalProfiled": 100,
    "capacityGap": 75841596,
    "majorPipeline": 47
  },
  "asOfDate": "2026-03-03T07:11:29"
}